py_dpm/__init__.py
py_dpm/api/__init__.py
py_dpm/api/dpm/__init__.py
py_dpm/api/dpm/data_dictionary.py
py_dpm/api/dpm/explorer.py
py_dpm/api/dpm/hierarchical_queries.py
py_dpm/api/dpm/instance.py
py_dpm/api/dpm/migration.py
py_dpm/api/dpm_xl/__init__.py
py_dpm/api/dpm_xl/ast_generator.py
py_dpm/api/dpm_xl/complete_ast.py
py_dpm/api/dpm_xl/operation_scopes.py
py_dpm/api/dpm_xl/semantic.py
py_dpm/api/dpm_xl/syntax.py
py_dpm/cli/__init__.py
py_dpm/cli/main.py
py_dpm/cli/commands/__init__.py
py_dpm/dpm/__init__.py
py_dpm/dpm/migration.py
py_dpm/dpm/models.py
py_dpm/dpm/utils.py
py_dpm/dpm/queries/base.py
py_dpm/dpm/queries/basic_objects.py
py_dpm/dpm/queries/explorer_queries.py
py_dpm/dpm/queries/filters.py
py_dpm/dpm/queries/glossary.py
py_dpm/dpm/queries/hierarchical_queries.py
py_dpm/dpm/queries/tables.py
py_dpm/dpm_xl/__init__.py
py_dpm/dpm_xl/semantic_analyzer.py
py_dpm/dpm_xl/symbols.py
py_dpm/dpm_xl/ast/__init__.py
py_dpm/dpm_xl/ast/constructor.py
py_dpm/dpm_xl/ast/ml_generation.py
py_dpm/dpm_xl/ast/module_analyzer.py
py_dpm/dpm_xl/ast/module_dependencies.py
py_dpm/dpm_xl/ast/nodes.py
py_dpm/dpm_xl/ast/operands.py
py_dpm/dpm_xl/ast/template.py
py_dpm/dpm_xl/ast/visitor.py
py_dpm/dpm_xl/ast/where_clause.py
py_dpm/dpm_xl/grammar/__init__.py
py_dpm/dpm_xl/grammar/generated/__init__.py
py_dpm/dpm_xl/grammar/generated/dpm_xlLexer.interp
py_dpm/dpm_xl/grammar/generated/dpm_xlLexer.py
py_dpm/dpm_xl/grammar/generated/dpm_xlLexer.tokens
py_dpm/dpm_xl/grammar/generated/dpm_xlParser.interp
py_dpm/dpm_xl/grammar/generated/dpm_xlParser.py
py_dpm/dpm_xl/grammar/generated/dpm_xlParser.tokens
py_dpm/dpm_xl/grammar/generated/dpm_xlParserListener.py
py_dpm/dpm_xl/grammar/generated/dpm_xlParserVisitor.py
py_dpm/dpm_xl/grammar/generated/listeners.py
py_dpm/dpm_xl/operators/__init__.py
py_dpm/dpm_xl/operators/aggregate.py
py_dpm/dpm_xl/operators/arithmetic.py
py_dpm/dpm_xl/operators/base.py
py_dpm/dpm_xl/operators/boolean.py
py_dpm/dpm_xl/operators/clause.py
pydpm_xl-0.2.12.dist-info/licenses/LICENSE
pydpm_xl-0.2.12.dist-info/METADATA
pydpm_xl-0.2.12.dist-info/WHEEL
pydpm_xl-0.2.12.dist-info/entry_points.txt
pydpm_xl-0.2.12.dist-info/top_level.txt
pydpm_xl-0.2.12.dist-info/RECORD
